armatis/__init__.py
armatis/models.py
armatis/parser.py
armatis/parsers/__init__.py
armatis/parsers/d2d.py
armatis/parsers/ems.py
armatis/parsers/epost.py
armatis/parsers/hanjin.py
armatis/parsers/hapdong.py
armatis/parsers/kg_logis.py
armatis/parsers/kgb.py
armatis/parsers/logen.py
armatis/parsers/lotte.py
armatis-1.1.1.dist-info/DESCRIPTION.rst
armatis-1.1.1.dist-info/METADATA
armatis-1.1.1.dist-info/RECORD
armatis-1.1.1.dist-info/WHEEL
armatis-1.1.1.dist-info/metadata.json
armatis-1.1.1.dist-info/top_level.txt
