Metadata-Version: 2.0
Name: armatis
Version: 1.1.1
Summary: Armatis parses the website or web API response of Korean parcel delivery service company for tracking the parcel.
Home-page: https://github.com/iBluemind/armatis
Author: Han Manjong
Author-email: han@manjong.org
License: BSD
Keywords: parcel delivery korea
Platform: UNKNOWN
Classifier: Development Status :: 5 - Production/Stable
Classifier: Intended Audience :: Developers
Classifier: Topic :: Software Development :: Libraries :: Python Modules
Classifier: License :: OSI Approved :: BSD License
Classifier: Programming Language :: Python :: 2
Classifier: Programming Language :: Python :: 2.7
Classifier: Programming Language :: Python :: 3
Classifier: Programming Language :: Python :: 3.3
Classifier: Programming Language :: Python :: 3.4
Classifier: Programming Language :: Python :: 3.5
Requires-Dist: beautifulsoup4
Requires-Dist: lxml
Requires-Dist: requests
Requires-Dist: six
